Metadata-Version: 2.1
Name: pd2slack
Version: 0.32
Summary: Syncs PD On-call to Slack User Group
Home-page: https://github.com/sidpremkumar/pd2slack
Author: Sid Premkumar
Author-email: sid.premkumar@gmail.com
License: UNKNOWN
Platform: UNKNOWN
License-File: LICENCE
